escrutinar_jp/__init__.py
escrutinar_jp/escrutinar.py
escrutinar_jp-0.0.4.dist-info/LICENSE
escrutinar_jp-0.0.4.dist-info/METADATA
escrutinar_jp-0.0.4.dist-info/WHEEL
escrutinar_jp-0.0.4.dist-info/top_level.txt
escrutinar_jp-0.0.4.dist-info/RECORD
