Metadata-Version: 2.1
Name: escrutinar-jp
Version: 0.0.4
Summary: pegar o IP de um determinado site, coletar dados de um determinado IP.
Home-page: https://github.com/JP-Linux/projeto_escrutinar
Author: Jorge Paulo
Author-email: jorgepsan7@gmail.com
License: UNKNOWN
Platform: UNKNOWN
Requires-Python: >=3.7
Requires-Dist: requests
